<?xml version="1.0" encoding="UTF-8"?>
<!DOCTYPE suite SYSTEM "http://testng.org/testng-1.0.dtd">
<suite name="Suite">
  <test thread-count="5" name="Test1">
    <classes>
      <class name="com.scp.maven.TestNg.CTest"/>
      <class name="com.scp.maven.TestNg.DTest"/>
      <class name="com.scp.maven.TestNg.BTest"/>
      <class name="com.scp.maven.TestNg.ATest"/>
    </classes>
  </test> <!-- Test -->
  
    <test thread-count="2" name="Test2">
    <classes>
      <class name="com.scp.maven.TestNg.BTest"/>
      <class name="com.scp.maven.TestNg.ATest"/>
    </classes>
  </test>
  
    <test thread-count="2" name="Test3">
    <classes>
      <class name="com.scp.maven.TestNg.CTest"/>
      <class name="com.scp.maven.TestNg.DTest"/>
    </classes>
  </test>
</suite> <!-- Suite -->
